{
  "$schema": "http://json-schema.org/draft-07/schema#",
  "title": "ThreadStartParams",
  "type": "object",
  "properties": {
    "approvalPolicy": {
      "anyOf": [
        {
          "$ref": "#/definitions/AskForApproval"
        },
        {
          "type": "null"
        }
      ]
    },
    "baseInstructions": {
      "type": [
        "string",
        "null"
      ]
    },
    "config": {
      "type": [
        "object",
        "null"
      ],
      "additionalProperties": true
    },
    "cwd": {
      "type": [
        "string",
        "null"
      ]
    },
    "developerInstructions": {
      "type": [
        "string",
        "null"
      ]
    },
    "experimentalRawEvents": {
      "description": "If true, opt into emitting raw response items on the event stream.\n\nThis is for internal use only (e.g. Codex Cloud). (TODO): Figure out a better way to categorize internal / experimental events & protocols.",
      "default": false,
      "type": "boolean"
    },
    "model": {
      "type": [
        "string",
        "null"
      ]
    },
    "modelProvider": {
      "type": [
        "string",
        "null"
      ]
    },
    "sandbox": {
      "anyOf": [
        {
          "$ref": "#/definitions/SandboxMode"
        },
        {
          "type": "null"
        }
      ]
    }
  },
  "definitions": {
    "AskForApproval": {
      "type": "string",
      "enum": [
        "untrusted",
        "on-failure",
        "on-request",
        "never"
      ]
    },
    "SandboxMode": {
      "type": "string",
      "enum": [
        "read-only",
        "workspace-write",
        "danger-full-access"
      ]
    }
  }
}